{
  "placeholderImages": [
    {
      "id": "user-1",
      "description": "Avatar for Jane Doe",
      "imageUrl": "https://picsum.photos/seed/user1/100/100",
      "imageHint": "woman portrait"
    },
    {
      "id": "user-2",
      "description": "Avatar for John Smith",
      "imageUrl": "https://images.unsplash.com/photo-1500648767791-00dcc994a43e?crop=entropy&cs=tinysrgb&fit=max&fm=jpg&ixid=M3w3NDE5ODJ8MHwxfHNlYXJjaHw2fHxtYW4lMjBwb3J0cmFpdHxlbnwwfHx8fDE3NTk3NzIxODV8MA&ixlib=rb-4.1.0&q=80&w=1080",
      "imageHint": "man portrait"
    },
    {
      "id": "user-3",
      "description": "Avatar for Emily Jones",
      "imageUrl": "https://images.unsplash.com/photo-1580489944761-15a19d654956?crop=entropy&cs=tinysrgb&fit=max&fm=jpg&ixid=M3w3NDE5ODJ8MHwxfHNlYXJjaHwyfHxwZXJzb24lMjBzbWlsaW5nfGVufDB8fHx8MTc1OTc3OTYxOXww&ixlib=rb-4.1.0&q=80&w=1080",
      "imageHint": "person smiling"
    },
    {
      "id": "user-4",
      "description": "Avatar for Michael Brown",
      "imageUrl": "https://images.unsplash.com/photo-1724814816550-195cfd07ec88?crop=entropy&cs=tinysrgb&fit=max&fm=jpg&ixid=M3w3NDE5ODJ8MHwxfHNlYXJjaHw3fHxmYXJtZXIlMjBwb3J0cmFpdHxlbnwwfHx8fDE3NTk3NzEwNjF8MA&ixlib=rb-4.1.0&q=80&w=1080",
      "imageHint": "farmer portrait"
    },
    {
      "id": "resource-1",
      "description": "A tractor in a field.",
      "imageUrl": "https://picsum.photos/seed/resource1/600/400",
      "imageHint": "tractor field"
    },
    {
      "id": "resource-2",
      "description": "Close-up of wheat.",
      "imageUrl": "https://picsum.photos/seed/resource2/600/400",
      "imageHint": "wheat crop"
    },
    {
      "id": "resource-3",
      "description": "An irrigation system in a field.",
      "imageUrl": "https://images.unsplash.com/photo-1692369584496-3216a88f94c1?crop=entropy&cs=tinysrgb&fit=max&fm=jpg&ixid=M3w3NDE5ODJ8MHwxfHNlYXJjaHwxfHxpcnJpZ2F0aW9uJTIwc3lzdGVtfGVufDB8fHx8MTc1OTc2NzY3MHww&ixlib=rb-4.1.0&q=80&w=1080",
      "imageHint": "irrigation system"
    },
    {
      "id": "resource-4",
      "description": "Person inspecting leaves for pests.",
      "imageUrl": "https://picsum.photos/seed/resource4/600/400",
      "imageHint": "pest control"
    },
    {
      "id": "resource-5",
      "description": "Soil in hands.",
      "imageUrl": "https://images.unsplash.com/photo-1603097208723-5da6f881858e?crop=entropy&cs=tinysrgb&fit=max&fm=jpg&ixid=M3w3NDE5ODJ8MHwxfHNlYXJjaHw5fHxoZWFsdGh5JTIwc29pbHxlbnwwfHx8fDE3NTk3NTQ5MDh8MA&ixlib=rb-4.1.0&q=80&w=1080",
      "imageHint": "healthy soil"
    },
    {
      "id": "resource-6",
      "description": "A modern greenhouse.",
      "imageUrl": "https://picsum.photos/seed/resource6/600/400",
      "imageHint": "modern greenhouse"
    },
    {
      "id": "login-background",
      "description": "A beautiful farm landscape at sunrise.",
      "imageUrl": "https://picsum.photos/seed/loginbg/1920/1080",
      "imageHint": "farm sunrise"
    }
  ]
}